{
  "Game": "/game",
  "UpdateGame": "/update-game",
  "DeleteGame": "/delete-game",
  "AddGame": "/add-game",
  "Games": "/games",

  "Genres": "/genres",
  "Genre": "/genre",
  "AddGenre": "/add-genre",
  "DeleteGenre": "/delete-genre",
  "UpdateGenre": "/update-genre",

  "UpdatePlatform": "/update-platform",
  "DeletePlatform": "/delete-platform",
  "Platform": "/platform",
  "AddPlatform": "/add-platform",
  "Platforms": "/platforms",

  "Publishers": "/publishers",
  "Publisher": "/publisher",
  "UpdatePublisher": "/update-publisher",
  "DeletePublisher": "/delete-publisher",
  "AddPublisher": "/add-publisher",

  "Order": "/order",
  "UpdateOrder": "/update-order",
  "History": "/history",
  "Orders": "/orders",
  "Basket": "/basket",
  "MakeOrder": "/order",

  "Users": "/users",
  "User": "/user",
  "UpdateUser": "/update-user",
  "DeleteUser": "/delete-user",
  "AddUser": "/add-user",
  "Login": "/login",
  "Notifications": "/Notifications",

  "Roles": "/roles",
  "Role": "/role",
  "UpdateRole": "/update-role",
  "DeleteRole": "/delete-role",
  "AddRole": "/add-role"
}
